EE4363/belmo057_EE4363_lab1/belmo057_EE4363_lab1.srcs/sources_1/imports/EE4363/mux_4to1.v
`timescale 1ns / 1ps


module mux4to1(out, a, b, c, d, s0, s1);
    input a, b, c, d, s0, s1;
    output out;
    wire e,f,w1,w2,w3,w4,w5,w6,w7,w8,w9,w10;
    not (e,s1);
    not (f,s0);
    
    and (w1,a,e);
    and (w2,b,e);
    and (w3,c,s1);
    and (w4,d,s1);
    
    and (w5,w1,f);
    and (w6,w2,s0);
    and (w7,w3,f);
    and (w8,w4,s0);
    
    or (w9,w5,w6);
    or (w10,w7,w8);
    or (out,w9,w10);
    
   
endmodule

EE4363/belmo057_EE4363_lab1/belmo057_EE4363_lab1.srcs/sources_1/imports/EE4363/comparator_1b.v
`timescale 1ns / 1ps


module comparator_1b(A, B, less_or_eq);
    input A, B;
    output less_or_eq;

    mux4to1 g1(less_or_eq, 1,1,0,1, B, A);
    
    
    
endmodule

EE4363/belmo057_EE4363_lab1/belmo057_EE4363_lab1.srcs/sources_1/imports/EE4363/comparator_4b.v
`timescale 1ns / 1ps


module comparator_4b(A, B, less_or_eq);
    input [3:0] A, B;
    output less_or_eq;
    wire w1, w2, w3;
    
    comparator_1b g1(A[3],B[3],w1);
    comparator_1b g2(A[2],B[2],w2);
    comparator_1b g3(A[1],B[1],w3);
    comparator_1b g4(A[0],B[0],less_or_eq);
    
endmodule

EE4363/tb_comparator_4b.v
module tb_comparator_4b;

wire less_or_eq;
reg [3:0] A, B;
integer i;

comparator_4b uut (
    .less_or_eq    (    less_or_eq    ),
    .A      (    A      ),
    .B (B)
);

parameter PERIOD = 4;
integer total_point = 0;

initial begin
    $dumpfile("db_tb_comparator_4b.vcd");
    $dumpvars(0, tb_comparator_4b);
    #(PERIOD/2);

    for (i=0; i<=2**8-1; i=i+1)begin
        A = i[3:0];
        B = i[7:4];
        #(PERIOD/2);
        
        if (A > B) begin
            if (less_or_eq == 0) total_point = total_point + 1;
        end
            
        else begin
            if (less_or_eq == 1) total_point = total_point + 1;
        end
        end
end

endmodule

EE4363/belmo057_EE4363_lab1/belmo057_EE4363_lab1.sim/sim_1/behav/xsim/db_tb_comparator_4b.vcd
$date
   Fri Oct  7 21:17:04 2022
$end
$version
  2022.1
$end
$timescale
  1ps
$end
$scope module tb_comparator_4b $end
$var wire 1 ! less_or_eq $end
$var reg 4 " A [3:0] $end
$var reg 4 # B [3:0] $end
$var integer 32 $ i [31:0] $end
$var integer 32 % total_point [31:0] $end
$scope module uut $end
$var wire 4 & A [3:0] $end
$var wire 4 ' B [3:0] $end
$var wire 1 ! less_or_eq $end
$var wire 1 ( w1 $end
$var wire 1 ) w2 $end
$var wire 1 * w3 $end
$scope module g1 $end
$var wire 1 + A $end
$var wire 1 , B $end
$var wire 1 ( less_or_eq $end
$scope module g1 $end
$var wire 1 - a $end
$var wire 1 . b $end
$var wire 1 / c $end
$var wire 1 0 d $end
$var wire 1 , s0 $end
$var wire 1 + s1 $end
$var wire 1 ( out $end
$var wire 1 1 e $end
$var wire 1 2 f $end
$var wire 1 3 w1 $end
$var wire 1 4 w2 $end
$var wire 1 5 w3 $end
$var wire 1 6 w4 $end
$var wire 1 7 w5 $end
$var wire 1 8 w6 $end
$var wire 1 9 w7 $end
$var wire 1 : w8 $end
$var wire 1 ; w9 $end
$var wire 1 < w10 $end
$upscope $end
$upscope $end
$scope module g2 $end
$var wire 1 = A $end
$var wire 1 ( B $end
$var wire 1 ) less_or_eq $end
$scope module g1 $end
$var wire 1 > a $end
$var wire 1 ? b $end
$var wire 1 @ c $end
$var wire 1 A d $end
$var wire 1 ( s0 $end
$var wire 1 = s1 $end
$var wire 1 ) out $end
$var wire 1 B e $end
$var wire 1 C f $end
$var wire 1 D w1 $end
$var wire 1 E w2 $end
$var wire 1 F w3 $end
$var wire 1 G w4 $end
$var wire 1 H w5 $end
$var wire 1 I w6 $end
$var wire 1 J w7 $end
$var wire 1 K w8 $end
$var wire 1 L w9 $end
$var wire 1 M w10 $end
$upscope $end
$upscope $end
$scope module g3 $end
$var wire 1 N A $end
$var wire 1 ) B $end
$var wire 1 * less_or_eq $end
$scope module g1 $end
$var wire 1 O a $end
$var wire 1 P b $end
$var wire 1 Q c $end
$var wire 1 R d $end
$var wire 1 ) s0 $end
$var wire 1 N s1 $end
$var wire 1 * out $end
$var wire 1 S e $end
$var wire 1 T f $end
$var wire 1 U w1 $end
$var wire 1 V w2 $end
$var wire 1 W w3 $end
$var wire 1 X w4 $end
$var wire 1 Y w5 $end
$var wire 1 Z w6 $end
$var wire 1 [ w7 $end
$var wire 1 \ w8 $end
$var wire 1 ] w9 $end
$var wire 1 ^ w10 $end
$upscope $end
$upscope $end
$scope module g4 $end
$var wire 1 _ A $end
$var wire 1 * B $end
$var wire 1 ! less_or_eq $end
$scope module g1 $end
$var wire 1 ` a $end
$var wire 1 a b $end
$var wire 1 b c $end
$var wire 1 c d $end
$var wire 1 * s0 $end
$var wire 1 _ s1 $end
$var wire 1 ! out $end
$var wire 1 d e $end
$var wire 1 e f $end
$var wire 1 f w1 $end
$var wire 1 g w2 $end
$var wire 1 h w3 $end
$var wire 1 i w4 $end
$var wire 1 j w5 $end
$var wire 1 k w6 $end
$var wire 1 l w7 $end
$var wire 1 m w8 $end
$var wire 1 n w9 $end
$var wire 1 o w10 $end
$upscope $end
$upscope $end
$upscope $end
$upscope $end
$enddefinitions $end
#0
$dumpvars
x!
bx "
bx #
bx $
b0 %
bx &
bx '
x(
x)
x*
x+
x,
1-
1.
0/
10
x1
x2
x3
x4
05
x6
x7
x8
09
x:
x;
x<
x=
1>
1?
0@
1A
xB
xC
xD
xE
0F
xG
xH
xI
0J
xK
xL
xM
xN
1O
1P
0Q
1R
xS
xT
xU
xV
0W
xX
xY
xZ
0[
x\
x]
x^
x_
1`
1a
0b
1c
xd
xe
xf
xg
0h
xi
xj
xk
0l
xm
xn
xo
$end
#2000
1!
b0 "
b0 #
b0 $
b0 &
b0 '
1(
1)
1*
0+
0,
11
12
13
14
05
06
17
08
09
0:
1;
0<
0=
1B
0C
1D
1E
0F
0G
0H
1I
0J
0K
1L
0M
0N
1S
0T
1U
1V
0W
0X
0Y
1Z
0[
0\
1]
0^
0_
1d
0e
1f
1g
0h
0i
0j
1k
0l
0m
1n
0o
#4000
b1 "
b0 #
b1 $
b1 %
b1 &
0+
0=
0N
1_
0d
0f
0g
0h
1i
0j
0k
1m
0n
1o
#6000
b10 "
b0 #
b10 $
b10 &
1*
0+
0=
1N
0S
0U
0V
0W
1X
0Y
0Z
1\
0]
1^
0_
1d
1f
1g
0h
0i
0j
1k
0m
1n
0o
#8000
b11 "
b0 #
b11 $
b11 &
0+
0=
1N
1_
0d
0f
0g
0h
1i
0j
0k
1m
0n
1o
#10000
b100 "
b0 #
b100 $
b100 &
1)
1*
0+
1=
0B
0D
0E
0F
1G
0H
0I
1K
0L
1M
0N
1S
1U
1V
0W
0X
0Y
1Z
0\
1]
0^
0_
1d
1f
1g
0h
0i
0j
1k
0m
1n
0o
#12000
b101 "
b0 #
b101 $
b101 &
0+
1=
0N
1_
0d
0f
0g
0h
1i
0j
0k
1m
0n
1o
#14000
b110 "
b0 #
b110 $
b110 &
1*
0+
1=
1N
0S
0U
0V
0W
1X
0Y
0Z
1\
0]
1^
0_
1d
1f
1g
0h
0i
0j
1k
0m
1n
0o
#16000
b111 "
b0 #
b111 $
b111 &
0+
1=
1N
1_
0d
0f
0g
0h
1i
0j
0k
1m
0n
1o
#18000
b1000 "
b0 #
b1000 $
b1000 &
0(
1)
1*
1+
01
03
04
05
16
07
08
0:
0;
0=
1B
1C
1D
1E
0F
0G
1H
0I
0J
0K
1L
0M
0N
1S
1U
1V
0W
0X
0Y
1Z
0\
1]
0^
0_
1d
1f
1g
0h
0i
0j
1k
0m
1n
0o
#20000
b1001 "
b0 #
b1001 $
b1001 &
1+
0=
0N
1_
0d
0f
0g
0h
1i
0j
0k
1m
0n
1o
#22000
b1010 "
b0 #
b1010 $
b1010 &
1*
1+
0=
1N
0S
0U
0V
0W
1X
0Y
0Z
1\
0]
1^
0_
1d
1f
1g
0h
0i
0j
1k
0m
1n
0o
#24000
b1011 "
b0 #
b1011 $
b1011 &
1+
0=
1N
1_
0d
0f
0g
0h
1i
0j
0k
1m
0n
1o
#26000
b1100 "
b0 #
b1100 $
b1100 &
0)
1*
1+
1=
0B
0D
0E
0F
1G
0H
0I
0K
0L
0N
1S
1T
1U
1V
0W
0X
1Y
0Z
0[
0\
1]
0^
0_
1d
1f
1g
0h
0i
0j
1k
0m
1n
0o
#28000
b1101 "
b0 #
b1101 $
b1101 &
1+
1=
0N
1_
0d
0f
0g
0h
1i
0j
0k
1m
0n
1o
#30000
b1110 "
b0 #
b1110 $
b1110 &
0*
1+
1=
1N
0S
0U
0V
0W
1X
0Y
0Z
0\
0]
0_
1d
1e
1f
1g
0h
0i
1j
0k
0l
0m
1n
0o
#32000
0!
b1111 "
b0 #
b1111 $
b1111 &
1+
1=
1N
1_
0d
0f
0g
0h
1i
0j
0k
0m
0n
#34000
1!
b0 "
b1 #
b10000 $
b10 %
b0 &
b1 '
1(
1)
1*
0+
0,
11
13
14
05
06
17
08
0:
1;
0=
1B
0C
1D
1E
0F
0G
0H
1I
0J
0K
1L
0N
1S
0T
1U
1V
0W
0X
0Y
1Z
0[
0\
1]
0_
1d
0e
1f
1g
0h
0i
0j
1k
0l
0m
1n
#36000
b1 "
b1 #
b10001 $
b11 %
b1 &
0+
0=
0N
1_
0d
0f
0g
0h
1i
0j
0k
1m
0n
1o
#38000
b10 "
b1 #
b10010 $
b100 %
b10 &
1*
0+
0=
1N
0S
0U
0V
0W
1X
0Y
0Z
1\
0]
1^
0_
1d
1f
1g
0h
0i
0j
1k
0m
1n
0o
#40000
b11 "
b1 #
b10011 $
b11 &
0+
0=
1N
1_
0d
0f
0g
0h
1i
0j
0k
1m
0n
1o
#42000
b100 "
b1 #
b10100 $
b100 &
1)
1*
0+
1=
0B
0D
0E
0F
1G
0H
0I
1K
0L
1M
0N
1S
1U
1V
0W
0X
0Y
1Z
0\
1]
0^
0_
1d
1f
1g
0h
0i
0j
1k
0m
1n
0o
#44000
b101 "
b1 #
b10101 $
b101 &
0+
1=
0N
1_
0d
0f
0g
0h
1i
0j
0k
1m
0n
1o
#46000
b110 "
b1 #
b10110 $
b110 &
1*
0+
1=
1N
0S
0U
0V
0W
1X
0Y
0Z
1\
0]
1^
0_
1d
1f
1g
0h
0i
0j
1k
0m
1n
0o
#48000
b111 "
b1 #
b10111 $
b111 &
0+
1=
1N
1_
0d
0f
0g
0h
1i
0j
0k
1m
0n
1o
#50000
b1000 "
b1 #
b11000 $
b1000 &
0(
1)
1*
1+
01
03
04
05
16
07
08
0:
0;
0=
1B
1C
1D
1E
0F
0G
1H
0I
0J
0K
1L
0M
0N
1S
1U
1V
0W
0X
0Y
1Z
0\
1]
0^
0_
1d
1f
1g
0h
0i
0j
1k
0m
1n
0o
#52000
b1001 "
b1 #
b11001 $
b1001 &
1+
0=
0N
1_
0d
0f
0g
0h
1i
0j
0k
1m
0n
1o
#54000
b1010 "
b1 #
b11010 $
b1010 &
1*
1+
0=
1N
0S
0U
0V
0W
1X
0Y
0Z
1\
0]
1^
0_
1d
1f
1g
0h
0i
0j
1k
0m
1n
0o
#56000
b1011 "
b1 #
b11011 $
b1011 &
1+
0=
1N
1_
0d
0f
0g
0h
1i
0j
0k
1m
0n
1o
#58000
b1100 "
b1 #
b11100 $
b1100 &
0)
1*
1+
1=
0B
0D
0E
0F
1G
0H
0I
0K
0L
0N
1S
1T
1U
1V
0W
0X
1Y
0Z
0[
0\
1]
0^
0_
1d
1f
1g
0h
0i
0j
1k
0m
1n
0o
#60000
b1101 "
b1 #
b11101 $
b1101 &
1+
1=
0N
1_
0d
0f
0g
0h
1i
0j
0k
1m
0n
1o
#62000
b1110 "
b1 #
b11110 $
b1110 &
0*
1+
1=
1N
0S
0U
0V
0W
1X
0Y
0Z
0\
0]
0_
1d
1e
1f
1g
0h
0i
1j
0k
0l
0m
1n
0o
#64000
0!
b1111 "
b1 #
b11111 $
b1111 &
1+
1=
1N
1_
0d
0f
0g
0h
1i
0j
0k
0m
0n
#66000
1!
b0 "
b10 #
b100000 $
b101 %
b0 &
b10 '
1(
1)
1*
0+
0,
11
13
14
05
06
17
08
0:
1;
0=
1B
0C
1D
1E
0F
0G
0H
1I
0J
0K
1L
0N
1S
0T
1U
1V
0W
0X
0Y
1Z
0[
0\
1]
0_
1d
0e
1f
1g
0h
0i
0j
1k
0l
0m
1n
#68000
b1 "
b10 #
b100001 $
b110 %
b1 &
0+
0=
0N
1_
0d
0f
0g
0h
1i
0j
0k
1m
0n
1o
#70000
b10 "
b10 #
b100010 $
b111 %
b10 &
1*
0+
0=
1N
0S
0U
0V
0W
1X
0Y
0Z
1\
0]
1^
0_
1d
1f
1g
0h
0i
0j
1k
0m
1n
0o
#72000
b11 "
b10 #
b100011 $
b1000 %
b11 &
0+
0=
1N
1_
0d
0f
0g
0h
1i
0j
0k
1m
0n
1o
#74000
b100 "
b10 #
b100100 $
b100 &
1)
1*
0+
1=
0B
0D
0E
0F
1G
0H
0I
1K
0L
1M
0N
1S
1U
1V
0W
0X
0Y
1Z
0\
1]
0^
0_
1d
1f
1g
0h
0i
0j
1k
0m
1n
0o
#76000
b101 "
b10 #
b100101 $
b101 &
0+
1=
0N
1_
0d
0f
0g
0h
1i
0j
0k
1m
0n
1o
#78000
b110 "
b10 #
b100110 $
b110 &
1*
0+
1=
1N
0S
0U
0V
0W
1X
0Y
0Z
1\
0]
1^
0_
1d
1f
1g
0h
0i
0j
1k
0m
1n
0o
#80000
b111 "
b10 #
b100111 $
b111 &
0+
1=
1N
1_
0d
0f
0g
0h
1i
0j
0k
1m
0n
1o
#82000
b1000 "
b10 #
b101000 $
b1000 &
0(
1)
1*
1+
01
03
04
05
16
07
08
0:
0;
0=
1B
1C
1D
1E
0F
0G
1H
0I
0J
0K
1L
0M
0N
1S
1U
1V
0W
0X
0Y
1Z
0\
1]
0^
0_
1d
1f
1g
0h
0i
0j
1k
0m
1n
0o
#84000
b1001 "
b10 #
b101001 $
b1001 &
1+
0=
0N
1_
0d
0f
0g
0h
1i
0j
0k
1m
0n
1o
#86000
b1010 "
b10 #
b101010 $
b1010 &
1*
1+
0=
1N
0S
0U
0V
0W
1X
0Y
0Z
1\
0]
1^
0_
1d
1f
1g
0h
0i
0j
1k
0m
1n
0o
#88000
b1011 "
b10 #
b101011 $
b1011 &
1+
0=
1N
1_
0d
0f
0g
0h
1i
0j
0k
1m
0n
1o
#90000
b1100 "
b10 #
b101100 $
b1100 &
0)
1*
1+
1=
0B
0D
0E
0F
1G
0H
0I
0K
0L
0N
1S
1T
1U
1V
0W
0X
1Y
0Z
0[
0\
1]
0^
0_
1d
1f
1g
0h
0i
0j
1k
0m
1n
0o
#92000
b1101 "
b10 #
b101101 $
b1101 &
1+
1=
0N
1_
0d
0f
0g
0h
1i
0j
0k
1m
0n
1o
#94000
b1110 "
b10 #
b101110 $
b1110 &
0*
1+
1=
1N
0S
0U
0V
0W
1X
0Y
0Z
0\
0]
0_
1d
1e
1f
1g
0h
0i
1j
0k
0l
0m
1n
0o
#96000
0!
b1111 "
b10 #
b101111 $
b1111 &
1+
1=
1N
1_
0d
0f
0g
0h
1i
0j
0k
0m
0n
#98000
1!
b0 "
b11 #
b110000 $
b1001 %
b0 &
b11 '
1(
1)
1*
0+
0,
11
13
14
05
06
17
08
0:
1;
0=
1B
0C
1D
1E
0F
0G
0H
1I
0J
0K
1L
0N
1S
0T
1U
1V
0W
0X
0Y
1Z
0[
0\
1]
0_
1d
0e
1f
1g
0h
0i
0j
1k
0l
0m
1n
#100000
b1 "
b11 #
b110001 $
b1010 %
b1 &
0+
0=
0N
1_
0d
0f
0g
0h
1i
0j
0k
1m
0n
1o
#102000
b10 "
b11 #
b110010 $
b1011 %
b10 &
1*
0+
0=
1N
0S
0U
0V
0W
1X
0Y
0Z
1\
0]
1^
0_
1d
1f
1g
0h
0i
0j
1k
0m
1n
0o
#104000
b11 "
b11 #
b110011 $
b1100 %
b11 &
0+
0=
1N
1_
0d
0f
0g
0h
1i
0j
0k
1m
0n
1o
#106000
b100 "
b11 #
b110100 $
b1101 %
b100 &
1)
1*
0+
1=
0B
0D
0E
0F
1G
0H
0I
1K
0L
1M
0N
1S
1U
1V
0W
0X
0Y
1Z
0\
1]
0^
0_
1d
1f
1g
0h
0i
0j
1k
0m
1n
0o
#108000
b101 "
b11 #
b110101 $
b101 &
0+
1=
0N
1_
0d
0f
0g
0h
1i
0j
0k
1m
0n
1o
#110000
b110 "
b11 #
b110110 $
b110 &
1*
0+
1=
1N
0S
0U
0V
0W
1X
0Y
0Z
1\
0]
1^
0_
1d
1f
1g
0h
0i
0j
1k
0m
1n
0o
#112000
b111 "
b11 #
b110111 $
b111 &
0+
1=
1N
1_
0d
0f
0g
0h
1i
0j
0k
1m
0n
1o
#114000
b1000 "
b11 #
b111000 $
b1000 &
0(
1)
1*
1+
01
03
04
05
16
07
08
0:
0;
0=
1B
1C
1D
1E
0F
0G
1H
0I
0J
0K
1L
0M
0N
1S
1U
1V
0W
0X
0Y
1Z
0\
1]
0^
0_
1d
1f
1g
0h
0i
0j
1k
0m
1n
0o
#116000
b1001 "
b11 #
b111001 $
b1001 &
1+
0=
0N
1_
0d
0f
0g
0h
1i
0j
0k
1m
0n
1o
#118000
b1010 "
b11 #
b111010 $
b1010 &
1*
1+
0=
1N
0S
0U
0V
0W
1X
0Y
0Z
1\
0]
1^
0_
1d
1f
1g
0h
0i
0j
1k
0m
1n
0o
#120000
b1011 "
b11 #
b111011 $
b1011 &
1+
0=
1N
1_
0d
0f
0g
0h
1i
0j
0k
1m
0n
1o
#122000
b1100 "
b11 #
b111100 $
b1100 &
0)
1*
1+
1=
0B
0D
0E
0F
1G
0H
0I
0K
0L
0N
1S
1T
1U
1V
0W
0X
1Y
0Z
0[
0\
1]
0^
0_
1d
1f
1g
0h
0i
0j
1k
0m
1n
0o
#124000
b1101 "
b11 #
b111101 $
b1101 &
1+
1=
0N
1_
0d
0f
0g
0h
1i
0j
0k
1m
0n
1o
#126000
b1110 "
b11 #
b111110 $
b1110 &
0*
1+
1=
1N
0S
0U
0V
0W
1X
0Y
0Z
0\
0]
0_
1d
1e
1f
1g
0h
0i
1j
0k
0l
0m
1n
0o
#128000
0!
b1111 "
b11 #
b111111 $
b1111 &
1+
1=
1N
1_
0d
0f
0g
0h
1i
0j
0k
0m
0n
#130000
1!
b0 "
b100 #
b1000000 $
b1110 %
b0 &
b100 '
1(
1)
1*
0+
0,
11
13
14
05
06
17
08
0:
1;
0=
1B
0C
1D
1E
0F
0G
0H
1I
0J
0K
1L
0N
1S
0T
1U
1V
0W
0X
0Y
1Z
0[
0\
1]
0_
1d
0e
1f
1g
0h
0i
0j
1k
0l
0m
1n
#132000
b1 "
b100 #
b1000001 $
b1111 %
b1 &
0+
0=
0N
1_
0d
0f
0g
0h
1i
0j
0k
1m
0n
1o
#134000
b10 "
b100 #
b1000010 $
b10000 %
b10 &
1*
0+
0=
1N
0S
0U
0V
0W
1X
0Y
0Z
1\
0]
1^
0_
1d
1f
1g
0h
0i
0j
1k
0m
1n
0o
#136000
b11 "
b100 #
b1000011 $
b10001 %
b11 &
0+
0=
1N
1_
0d
0f
0g
0h
1i
0j
0k
1m
0n
1o
#138000
b100 "
b100 #
b1000100 $
b10010 %
b100 &
1)
1*
0+
1=
0B
0D
0E
0F
1G
0H
0I
1K
0L
1M
0N
1S
1U
1V
0W
0X
0Y
1Z
0\
1]
0^
0_
1d
1f
1g
0h
0i
0j
1k
0m
1n
0o
#140000
b101 "
b100 #
b1000101 $
b10011 %
b101 &
0+
1=
0N
1_
0d
0f
0g
0h
1i
0j
0k
1m
0n
1o
#142000
b110 "
b100 #
b1000110 $
b110 &
1*
0+
1=
1N
0S
0U
0V
0W
1X
0Y
0Z
1\
0]
1^
0_
1d
1f
1g
0h
0i
0j
1k
0m
1n
0o
#144000
b111 "
b100 #
b1000111 $
b111 &
0+
1=
1N
1_
0d
0f
0g
0h
1i
0j
0k
1m
0n
1o
#146000
b1000 "
b100 #
b1001000 $
b1000 &
0(
1)
1*
1+
01
03
04
05
16
07
08
0:
0;
0=
1B
1C
1D
1E
0F
0G
1H
0I
0J
0K
1L
0M
0N
1S
1U
1V
0W
0X
0Y
1Z
0\
1]
0^
0_
1d
1f
1g
0h
0i
0j
1k
0m
1n
0o
#148000
b1001 "
b100 #
b1001001 $
b1001 &
1+
0=
0N
1_
0d
0f
0g
0h
1i
0j
0k
1m
0n
1o
#150000
b1010 "
b100 #
b1001010 $
b1010 &
1*
1+
0=
1N
0S
0U
0V
0W
1X
0Y
0Z
1\
0]
1^
0_
1d
1f
1g
0h
0i
0j
1k
0m
1n
0o
#152000
b1011 "
b100 #
b1001011 $
b1011 &
1+
0=
1N
1_
0d
0f
0g
0h
1i
0j
0k
1m
0n
1o
#154000
b1100 "
b100 #
b1001100 $
b1100 &
0)
1*
1+
1=
0B
0D
0E
0F
1G
0H
0I
0K
0L
0N
1S
1T
1U
1V
0W
0X
1Y
0Z
0[
0\
1]
0^
0_
1d
1f
1g
0h
0i
0j
1k
0m
1n
0o
#156000
b1101 "
b100 #
b1001101 $
b1101 &
1+
1=
0N
1_
0d
0f
0g
0h
1i
0j
0k
1m
0n
1o
#158000
b1110 "
b100 #
b1001110 $
b1110 &
0*
1+
1=
1N
0S
0U
0V
0W
1X
0Y
0Z
0\
0]
0_
1d
1e
1f
1g
0h
0i
1j
0k
0l
0m
1n
0o
#160000
0!
b1111 "
b100 #
b1001111 $
b1111 &
1+
1=
1N
1_
0d
0f
0g
0h
1i
0j
0k
0m
0n
#162000
1!
b0 "
b101 #
b1010000 $
b10100 %
b0 &
b101 '
1(
1)
1*
0+
0,
11
13
14
05
06
17
08
0:
1;
0=
1B
0C
1D
1E
0F
0G
0H
1I
0J
0K
1L
0N
1S
0T
1U
1V
0W
0X
0Y
1Z
0[
0\
1]
0_
1d
0e
1f
1g
0h
0i
0j
1k
0l
0m
1n
#164000
b1 "
b101 #
b1010001 $
b10101 %
b1 &
0+
0=
0N
1_
0d
0f
0g
0h
1i
0j
0k
1m
0n
1o
#166000
b10 "
b101 #
b1010010 $
b10110 %
b10 &
1*
0+
0=
1N
0S
0U
0V
0W
1X
0Y
0Z
1\
0]
1^
0_
1d
1f
1g
0h
0i
0j
1k
0m
1n
0o
#168000
b11 "
b101 #
b1010011 $
b10111 %
b11 &
0+
0=
1N
1_
0d
0f
0g
0h
1i
0j
0k
1m
0n
1o
#170000
b100 "
b101 #
b1010100 $
b11000 %
b100 &
1)
1*
0+
1=
0B
0D
0E
0F
1G
0H
0I
1K
0L
1M
0N
1S
1U
1V
0W
0X
0Y
1Z
0\
1]
0^
0_
1d
1f
1g
0h
0i
0j
1k
0m
1n
0o
#172000
b101 "
b101 #
b1010101 $
b11001 %
b101 &
0+
1=
0N
1_
0d
0f
0g
0h
1i
0j
0k
1m
0n
1o
#174000
b110 "
b101 #
b1010110 $
b11010 %
b110 &
1*
0+
1=
1N
0S
0U
0V
0W
1X
0Y
0Z
1\
0]
1^
0_
1d
1f
1g
0h
0i
0j
1k
0m
1n
0o
#176000
b111 "
b101 #
b1010111 $
b111 &
0+
1=
1N
1_
0d
0f
0g
0h
1i
0j
0k
1m
0n
1o
#178000
b1000 "
b101 #
b1011000 $
b1000 &
0(
1)
1*
1+
01
03
04
05
16
07
08
0:
0;
0=
1B
1C
1D
1E
0F
0G
1H
0I
0J
0K
1L
0M
0N
1S
1U
1V
0W
0X
0Y
1Z
0\
1]
0^
0_
1d
1f
1g
0h
0i
0j
1k
0m
1n
0o
#180000
b1001 "
b101 #
b1011001 $
b1001 &
1+
0=
0N
1_
0d
0f
0g
0h
1i
0j
0k
1m
0n
1o
#182000
b1010 "
b101 #
b1011010 $
b1010 &
1*
1+
0=
1N
0S
0U
0V
0W
1X
0Y
0Z
1\
0]
1^
0_
1d
1f
1g
0h
0i
0j
1k
0m
1n
0o
#184000
b1011 "
b101 #
b1011011 $
b1011 &
1+
0=
1N
1_
0d
0f
0g
0h
1i
0j
0k
1m
0n
1o
#186000
b1100 "
b101 #
b1011100 $
b1100 &
0)
1*
1+
1=
0B
0D
0E
0F
1G
0H
0I
0K
0L
0N
1S
1T
1U
1V
0W
0X
1Y
0Z
0[
0\
1]
0^
0_
1d
1f
1g
0h
0i
0j
1k
0m
1n
0o
#188000
b1101 "
b101 #
b1011101 $
b1101 &
1+
1=
0N
1_
0d
0f
0g
0h
1i
0j
0k
1m
0n
1o
#190000
b1110 "
b101 #
b1011110 $
b1110 &
0*
1+
1=
1N
0S
0U
0V
0W
1X
0Y
0Z
0\
0]
0_
1d
1e
1f
1g
0h
0i
1j
0k
0l
0m
1n
0o
#192000
0!
b1111 "
b101 #
b1011111 $
b1111 &
1+
1=
1N
1_
0d
0f
0g
0h
1i
0j
0k
0m
0n
#194000
1!
b0 "
b110 #
b1100000 $
b11011 %
b0 &
b110 '
1(
1)
1*
0+
0,
11
13
14
05
06
17
08
0:
1;
0=
1B
0C
1D
1E
0F
0G
0H
1I
0J
0K
1L
0N
1S
0T
1U
1V
0W
0X
0Y
1Z
0[
0\
1]
0_
1d
0e
1f
1g
0h
0i
0j
1k
0l
0m
1n
#196000
b1 "
b110 #
b1100001 $
b11100 %
b1 &
0+
0=
0N
1_
0d
0f
0g
0h
1i
0j
0k
1m
0n
1o
#198000
b10 "
b110 #
b1100010 $
b11101 %
b10 &
1*
0+
0=
1N
0S
0U
0V
0W
1X
0Y
0Z
1\
0]
1^
0_
1d
1f
1g
0h
0i
0j
1k
0m
1n
0o
#200000
b11 "
b110 #
b1100011 $
b11110 %
b11 &
0+
0=
1N
1_
0d
0f
0g
0h
1i
0j
0k
1m
0n
1o
#202000
b100 "
b110 #
b1100100 $
b11111 %
b100 &
1)
1*
0+
1=
0B
0D
0E
0F
1G
0H
0I
1K
0L
1M
0N
1S
1U
1V
0W
0X
0Y
1Z
0\
1]
0^
0_
1d
1f
1g
0h
0i
0j
1k
0m
1n
0o
#204000
b101 "
b110 #
b1100101 $
b100000 %
b101 &
0+
1=
0N
1_
0d
0f
0g
0h
1i
0j
0k
1m
0n
1o
#206000
b110 "
b110 #
b1100110 $
b100001 %
b110 &
1*
0+
1=
1N
0S
0U
0V
0W
1X
0Y
0Z
1\
0]
1^
0_
1d
1f
1g
0h
0i
0j
1k
0m
1n
0o
#208000
b111 "
b110 #
b1100111 $
b100010 %
b111 &
0+
1=
1N
1_
0d
0f
0g
0h
1i
0j
0k
1m
0n
1o
#210000
b1000 "
b110 #
b1101000 $
b1000 &
0(
1)
1*
1+
01
03
04
05
16
07
08
0:
0;
0=
1B
1C
1D
1E
0F
0G
1H
0I
0J
0K
1L
0M
0N
1S
1U
1V
0W
0X
0Y
1Z
0\
1]
0^
0_
1d
1f
1g
0h
0i
0j
1k
0m
1n
0o
#212000
b1001 "
b110 #
b1101001 $
b1001 &
1+
0=
0N
1_
0d
0f
0g
0h
1i
0j
0k
1m
0n
1o
#214000
b1010 "
b110 #
b1101010 $
b1010 &
1*
1+
0=
1N
0S
0U
0V
0W
1X
0Y
0Z
1\
0]
1^
0_
1d
1f
1g
0h
0i
0j
1k
0m
1n
0o
#216000
b1011 "
b110 #
b1101011 $
b1011 &
1+
0=
1N
1_
0d
0f
0g
0h
1i
0j
0k
1m
0n
1o
#218000
b1100 "
b110 #
b1101100 $
b1100 &
0)
1*
1+
1=
0B
0D
0E
0F
1G
0H
0I
0K
0L
0N
1S
1T
1U
1V
0W
0X
1Y
0Z
0[
0\
1]
0^
0_
1d
1f
1g
0h
0i
0j
1k
0m
1n
0o
#220000
b1101 "
b110 #
b1101101 $
b1101 &
1+
1=
0N
1_
0d
0f
0g
0h
1i
0j
0k
1m
0n
1o
#222000
b1110 "
b110 #
b1101110 $
b1110 &
0*
1+
1=
1N
0S
0U
0V
0W
1X
0Y
0Z
0\
0]
0_
1d
1e
1f
1g
0h
0i
1j
0k
0l
0m
1n
0o
#224000
0!
b1111 "
b110 #
b1101111 $
b1111 &
1+
1=
1N
1_
0d
0f
0g
0h
1i
0j
0k
0m
0n
#226000
1!
b0 "
b111 #
b1110000 $
b100011 %
b0 &
b111 '
1(
1)
1*
0+
0,
11
13
14
05
06
17
08
0:
1;
0=
1B
0C
1D
1E
0F
0G
0H
1I
0J
0K
1L
0N
1S
0T
1U
1V
0W
0X
0Y
1Z
0[
0\
1]
0_
1d
0e
1f
1g
0h
0i
0j
1k
0l
0m
1n
#228000
b1 "
b111 #
b1110001 $
b100100 %
b1 &
0+
0=
0N
1_
0d
0f
0g
0h
1i
0j
0k
1m
0n
1o
#230000
b10 "
b111 #
b1110010 $
b100101 %
b10 &
1*
0+
0=
1N
0S
0U
0V
0W
1X
0Y
0Z
1\
0]
1^
0_
1d
1f
1g
0h
0i
0j
1k
0m
1n
0o
#232000
b11 "
b111 #
b1110011 $
b100110 %
b11 &
0+
0=
1N
1_
0d
0f
0g
0h
1i
0j
0k
1m
0n
1o
#234000
b100 "
b111 #
b1110100 $
b100111 %
b100 &
1)
1*
0+
1=
0B
0D
0E
0F
1G
0H
0I
1K
0L
1M
0N
1S
1U
1V
0W
0X
0Y
1Z
0\
1]
0^
0_
1d
1f
1g
0h
0i
0j
1k
0m
1n
0o
#236000
b101 "
b111 #
b1110101 $
b101000 %
b101 &
0+
1=
0N
1_
0d
0f
0g
0h
1i
0j
0k
1m
0n
1o
