EE4363/belmo057_EE4363_lab1/belmo057_EE4363_lab1.srcs/sources_1/imports/EE4363/mux_4to1.v
`timescale 1ns / 1ps

module mux4to1(out, a, b, c, d, s0, s1);
    input a, b, c, d, s0, s1;
    output out;
    wire e,f,w1,w2,w3,w4,w5,w6,w7,w8,w9,w10;
    not (e,s1);
    not (f,s0);
    
    and (w1,a,e);
    and (w2,b,e);
    and (w3,c,s1);
    and (w4,d,s1);
    
    and (w5,w1,f);
    and (w6,w2,s0);
    and (w7,w3,f);
    and (w8,w4,s0);
    
    or (w9,w5,w6);
    or (w10,w7,w8);
    or (out,w9,w10);
    
   
endmodule

EE4363/belmo057_EE4363_lab1/belmo057_EE4363_lab1.srcs/sources_1/imports/EE4363/mux_16to1.v
`timescale 1ns / 1ps


module mux16to1(D, control, out);
    input [15:0] D;
    input [3:0] control;
    output out;
    wire w1,w2,w3,w4;
    
        
    mux4to1 g1(w1,D[0],D[1],D[2],D[3],control[1],control[0]);
    mux4to1 g2(w2,D[4],D[5],D[6],D[7],control[1],control[0]);
    mux4to1 g3(w3,D[8],D[9],D[10],D[11],control[1],control[0]);
    mux4to1 g4(w4,D[12],D[13],D[14],D[15],control[1],control[0]);
    
    mux4to1 g5(out, w1, w2, w3, w4, control[1], control[2]);
    

endmodule

EE4363/belmo057_EE4363_lab1/belmo057_EE4363_lab1.srcs/sources_1/imports/EE4363/tb_mux16to1.v
module tb_mux16to1;

reg clk;
wire out;
reg [15:0] D;
reg [3:0] control;
integer i;

mux16to1 uut (
    .out    (    out    ),
    .D      (    D      ),
    .control (control)
);

parameter PERIOD = 20;
integer total_point = 0;

initial begin
    $dumpfile("db_tb_mux16to1.vcd");
    $dumpvars(0, tb_mux16to1);
    clk = 1'b0;
    #(PERIOD/2);
    
    D = 16'b1010101010101010;

    for (i=0; i<=2**4-1; i=i+1)begin
        control = i[3:0];
        #(PERIOD/2);
        
        case ({control})
        0: begin
            if (out == D[0]) begin total_point = total_point+1;end
//            break;
            end
        1: begin
            if (out == D[1]) begin total_point = total_point+1;end
//            break;
            end
        2: begin
            if (out == D[2]) begin total_point = total_point+1;end
//            break;
            end
        3: begin
            if (out == D[3]) begin total_point = total_point+1;end
//            break;
            end
        4: begin
            if (out == D[4]) begin total_point = total_point+1;end
//            break;
            end
        5: begin
            if (out == D[5]) begin total_point = total_point+1;end
//            break;
            end
        6: begin
            if (out == D[6]) begin total_point = total_point+1;end
//            break;
            end
        7: begin
            if (out == D[7]) begin total_point = total_point+1;end
//            break;
            end
        8: begin
            if (out == D[8]) begin total_point = total_point+1;end
//            break;
            end
        9: begin
            if (out == D[9]) begin total_point = total_point+1;end
//            break;
            end
        10: begin
            if (out == D[10]) begin total_point = total_point+1;end
//            break;
            end
        11: begin
            if (out == D[11]) begin total_point = total_point+1;end
//            break;
            end
        12: begin
            if (out == D[12]) begin total_point = total_point+1;end
//            break;
            end
        13: begin
            if (out == D[13]) begin total_point = total_point+1;end
//            break;
            end
        14: begin
            if (out == D[14]) begin total_point = total_point+1;end
//            break;
            end
        15: begin
            if (out == D[15]) begin total_point = total_point+1;end
//            break;
            end
        default: ;//break;
        endcase
        
        end
end

endmodule

EE4363/belmo057_EE4363_lab1/belmo057_EE4363_lab1.sim/sim_1/behav/xsim/db_tb_mux16to1.vcd
$date
   Fri Sep 30 16:57:04 2022
$end
$version
  2022.1
$end
$timescale
  1ps
$end
$scope module tb_mux16to1 $end
$var reg 1 ! clk $end
$var wire 1 " out $end
$var reg 16 # D [15:0] $end
$var reg 4 $ control [3:0] $end
$var integer 32 % i [31:0] $end
$var integer 32 & total_point [31:0] $end
$scope module uut $end
$var wire 16 ' D [15:0] $end
$var wire 4 ( control [3:0] $end
$var wire 1 " out $end
$var wire 1 ) w1 $end
$var wire 1 * w2 $end
$var wire 1 + w3 $end
$var wire 1 , w4 $end
$scope module g1 $end
$var wire 1 - a $end
$var wire 1 . b $end
$var wire 1 / c $end
$var wire 1 0 d $end
$var wire 1 1 s0 $end
$var wire 1 2 s1 $end
$var wire 1 ) out $end
$var wire 1 3 e $end
$var wire 1 4 f $end
$var wire 1 5 w1 $end
$var wire 1 6 w2 $end
$var wire 1 7 w3 $end
$var wire 1 8 w4 $end
$var wire 1 9 w5 $end
$var wire 1 : w6 $end
$var wire 1 ; w7 $end
$var wire 1 < w8 $end
$var wire 1 = w9 $end
$var wire 1 > w10 $end
$upscope $end
$scope module g2 $end
$var wire 1 ? a $end
$var wire 1 @ b $end
$var wire 1 A c $end
$var wire 1 B d $end
$var wire 1 1 s0 $end
$var wire 1 2 s1 $end
$var wire 1 * out $end
$var wire 1 C e $end
$var wire 1 D f $end
$var wire 1 E w1 $end
$var wire 1 F w2 $end
$var wire 1 G w3 $end
$var wire 1 H w4 $end
$var wire 1 I w5 $end
$var wire 1 J w6 $end
$var wire 1 K w7 $end
$var wire 1 L w8 $end
$var wire 1 M w9 $end
$var wire 1 N w10 $end
$upscope $end
$scope module g3 $end
$var wire 1 O a $end
$var wire 1 P b $end
$var wire 1 Q c $end
$var wire 1 R d $end
$var wire 1 1 s0 $end
$var wire 1 2 s1 $end
$var wire 1 + out $end
$var wire 1 S e $end
$var wire 1 T f $end
$var wire 1 U w1 $end
$var wire 1 V w2 $end
$var wire 1 W w3 $end
$var wire 1 X w4 $end
$var wire 1 Y w5 $end
$var wire 1 Z w6 $end
$var wire 1 [ w7 $end
$var wire 1 \ w8 $end
$var wire 1 ] w9 $end
$var wire 1 ^ w10 $end
$upscope $end
$scope module g4 $end
$var wire 1 _ a $end
$var wire 1 ` b $end
$var wire 1 a c $end
$var wire 1 b d $end
$var wire 1 1 s0 $end
$var wire 1 2 s1 $end
$var wire 1 , out $end
$var wire 1 c e $end
$var wire 1 d f $end
$var wire 1 e w1 $end
$var wire 1 f w2 $end
$var wire 1 g w3 $end
$var wire 1 h w4 $end
$var wire 1 i w5 $end
$var wire 1 j w6 $end
$var wire 1 k w7 $end
$var wire 1 l w8 $end
$var wire 1 m w9 $end
$var wire 1 n w10 $end
$upscope $end
$scope module g5 $end
$var wire 1 ) a $end
$var wire 1 * b $end
$var wire 1 + c $end
$var wire 1 , d $end
$var wire 1 1 s0 $end
$var wire 1 o s1 $end
$var wire 1 " out $end
$var wire 1 p e $end
$var wire 1 q f $end
$var wire 1 r w1 $end
$var wire 1 s w2 $end
$var wire 1 t w3 $end
$var wire 1 u w4 $end
$var wire 1 v w5 $end
$var wire 1 w w6 $end
$var wire 1 x w7 $end
$var wire 1 y w8 $end
$var wire 1 z w9 $end
$var wire 1 { w10 $end
$upscope $end
$upscope $end
$upscope $end
$enddefinitions $end
#0
$dumpvars
0!
x"
bx #
bx $
bx %
b0 &
bx '
bx (
x)
x*
x+
x,
x-
x.
x/
x0
x1
x2
x3
x4
x5
x6
x7
x8
x9
x:
x;
x<
x=
x>
x?
x@
xA
xB
xC
xD
xE
xF
xG
xH
xI
xJ
xK
xL
xM
xN
xO
xP
xQ
xR
xS
xT
xU
xV
xW
xX
xY
xZ
x[
x\
x]
x^
x_
x`
xa
xb
xc
xd
xe
xf
xg
xh
xi
xj
xk
xl
xm
xn
xo
xp
xq
xr
xs
xt
xu
xv
xw
xx
xy
xz
x{
$end
#10000
0"
b1010101010101010 #
b0 $
b0 %
b1010101010101010 '
b0 (
0)
0*
0+
0,
0-
1.
0/
10
01
02
13
14
05
16
07
08
09
0:
0;
0<
0=
0>
0?
1@
0A
1B
1C
1D
0E
1F
0G
0H
0I
0J
0K
0L
0M
0N
0O
1P
0Q
1R
1S
1T
0U
1V
0W
0X
0Y
0Z
0[
0\
0]
0^
0_
1`
0a
1b
1c
1d
0e
1f
0g
0h
0i
0j
0k
0l
0m
0n
0o
1p
1q
0r
0s
0t
0u
0v
0w
0x
0y
0z
0{
#20000
b1 $
b1 %
b1 &
b1 (
01
12
03
05
06
07
18
0:
0<
0C
0E
0F
0G
1H
0J
0L
0S
0U
0V
0W
1X
0Z
0\
0c
0e
0f
0g
1h
0j
0l
0o
#30000
1"
b10 $
b10 %
b10 (
1)
1*
1+
1,
11
02
13
04
05
16
07
08
09
1:
0;
0<
1=
1C
0D
0E
1F
0G
0H
0I
1J
0K
0L
1M
1S
0T
0U
1V
0W
0X
0Y
1Z
0[
0\
1]
1c
0d
0e
1f
0g
0h
0i
1j
0k
0l
1m
0o
0q
1r
1s
0t
0u
0v
1w
0x
0y
1z
#40000
b11 $
b11 %
b11 (
1)
1*
1+
1,
11
12
03
05
06
07
18
0:
1<
0=
1>
0C
0E
0F
0G
1H
0J
1L
0M
1N
0S
0U
0V
0W
1X
0Z
1\
0]
1^
0c
0e
0f
0g
1h
0j
1l
0m
1n
0o
#50000
0"
b100 $
b100 %
b10 &
b100 (
0)
0*
0+
0,
01
02
13
14
05
16
07
08
09
0:
0;
0<
0>
1C
1D
0E
1F
0G
0H
0I
0J
0K
0L
0N
1S
1T
0U
1V
0W
0X
0Y
0Z
0[
0\
0^
1c
1d
0e
1f
0g
0h
0i
0j
0k
0l
0n
1o
0p
1q
0r
0s
0t
0u
0v
0w
0x
0y
0z
0{
#60000
b101 $
b101 %
b11 &
b101 (
01
12
03
05
06
07
18
0:
0<
0C
0E
0F
0G
1H
0J
0L
0S
0U
0V
0W
1X
0Z
0\
0c
0e
0f
0g
1h
0j
0l
1o
#70000
1"
b110 $
b110 %
b110 (
1)
1*
1+
1,
11
02
13
04
05
16
07
08
09
1:
0;
0<
1=
1C
0D
0E
1F
0G
0H
0I
1J
0K
0L
1M
1S
0T
0U
1V
0W
0X
0Y
1Z
0[
0\
1]
1c
0d
0e
1f
0g
0h
0i
1j
0k
0l
1m
1o
0q
0r
0s
1t
1u
0v
0w
0x
1y
1{
#80000
b111 $
b111 %
b111 (
1)
1*
1+
1,
11
12
03
05
06
07
18
0:
1<
0=
1>
0C
0E
0F
0G
1H
0J
1L
0M
1N
0S
0U
0V
0W
1X
0Z
1\
0]
1^
0c
0e
0f
0g
1h
0j
1l
0m
1n
1o
#90000
0"
b1000 $
b1000 %
b100 &
b1000 (
0)
0*
0+
0,
01
02
13
14
05
16
07
08
09
0:
0;
0<
0>
1C
1D
0E
1F
0G
0H
0I
0J
0K
0L
0N
1S
1T
0U
1V
0W
0X
0Y
0Z
0[
0\
0^
1c
1d
0e
1f
0g
0h
0i
0j
0k
0l
0n
0o
1p
1q
0r
0s
0t
0u
0v
0w
0x
0y
0z
0{
#100000
b1001 $
b1001 %
b101 &
b1001 (
01
12
03
05
06
07
18
0:
0<
0C
0E
0F
0G
1H
0J
0L
0S
0U
0V
0W
1X
0Z
0\
0c
0e
0f
0g
1h
0j
0l
0o
#110000
1"
b1010 $
b1010 %
b1010 (
1)
1*
1+
1,
11
02
13
04
05
16
07
08
09
1:
0;
0<
1=
1C
0D
0E
1F
0G
0H
0I
1J
0K
0L
1M
1S
0T
0U
1V
0W
0X
0Y
1Z
0[
0\
1]
1c
0d
0e
1f
0g
0h
0i
1j
0k
0l
1m
0o
0q
1r
1s
0t
0u
0v
1w
0x
0y
1z
#120000
b1011 $
b1011 %
b1011 (
1)
1*
1+
1,
11
12
03
05
06
07
18
0:
1<
0=
1>
0C
0E
0F
0G
1H
0J
1L
0M
1N
0S
0U
0V
0W
1X
0Z
1\
0]
1^
0c
0e
0f
0g
1h
0j
1l
0m
1n
0o
#130000
0"
b1100 $
b1100 %
b110 &
b1100 (
0)
0*
0+
0,
01
02
13
14
05
16
07
08
09
0:
0;
0<
0>
1C
1D
0E
1F
0G
0H
0I
0J
0K
0L
0N
1S
1T
0U
1V
0W
0X
0Y
0Z
0[
0\
0^
1c
1d
0e
1f
0g
0h
0i
0j
0k
0l
0n
1o
0p
1q
0r
0s
0t
0u
0v
0w
0x
0y
0z
0{
#140000
b1101 $
b1101 %
b111 &
b1101 (
01
12
03
05
06
07
18
0:
0<
0C
0E
0F
0G
1H
0J
0L
0S
0U
0V
0W
1X
0Z
0\
0c
0e
0f
0g
1h
0j
0l
1o
#150000
1"
b1110 $
b1110 %
b1110 (
1)
1*
1+
1,
11
02
13
04
05
16
07
08
09
1:
0;
0<
1=
1C
0D
0E
1F
0G
0H
0I
1J
0K
0L
1M
1S
0T
0U
1V
0W
0X
0Y
1Z
0[
0\
1]
1c
0d
0e
1f
0g
0h
0i
1j
0k
0l
1m
1o
0q
0r
0s
1t
1u
0v
0w
0x
1y
1{
#160000
b1111 $
b1111 %
b1111 (
1)
1*
1+
1,
11
12
03
05
06
07
18
0:
1<
0=
1>
0C
0E
0F
0G
1H
0J
1L
0M
1N
0S
0U
0V
0W
1X
0Z
1\
0]
1^
0c
0e
0f
0g
1h
0j
1l
0m
1n
1o
#170000
b10000 %
b1000 &
