EE4363/belmo057_EE4363_lab1/belmo057_EE4363_lab1.srcs/sources_1/imports/EE4363/mux_4to1.v
`timescale 1ns / 1ps

module mux4to1(out, a, b, c, d, s0, s1);
    input a, b, c, d, s0, s1;
    output out;
    wire e,f,w1,w2,w3,w4,w5,w6,w7,w8,w9,w10;
    not (e,s1);
    not (f,s0);
    
    and (w1,a,e);
    and (w2,b,e);
    and (w3,c,s1);
    and (w4,d,s1);
    
    and (w5,w1,f);
    and (w6,w2,s0);
    and (w7,w3,f);
    and (w8,w4,s0);
    
    or (w9,w5,w6);
    or (w10,w7,w8);
    or (out,w9,w10);
    
   
endmodule

EE4363/tb_mux4to1.v
module tb_mux4to1;

reg clk;
wire out;
reg a, b, c, d, s0, s1;
integer i;

mux4to1 uut (
    .out    (    out    ),
    .a      (    a      ),
    .b (b),
    .c (c),
    .d (d),
    .s0 (s0),
    .s1 (s1)
);

parameter PERIOD = 20;
integer total_point = 0;

initial begin
    $dumpfile("db_tb_mux4to1.vcd");
    $dumpvars(0, tb_mux4to1);
    clk = 1'b0;
    #(PERIOD/2);

    for (i=0; i<=63; i=i+1)begin
        a = i[0];
        b = i[1];
        c = i[2];
        d = i[3];
        s0 = i[4];
        s1 = i[5];
        #(PERIOD/2);
        
        case ({s1, s0})
        0: begin
            if (out == a) begin total_point = total_point+1;end
//            break;
            end
        1: begin
            if (out == b) begin total_point = total_point+1;end
//            break;
            end
        2: begin
            if (out == c) begin total_point = total_point+1;end
//            break;
            end
        3: begin
            if (out == d) begin total_point = total_point+1;end
//            break;
            end
        default: ;//break;
        endcase
        
        end
end

endmodule

EE4363/belmo057_EE4363_lab1/belmo057_EE4363_lab1.sim/sim_1/behav/xsim/db_tb_mux4to1.vcd
$date
   Fri Sep 30 16:51:19 2022
$end
$version
  2022.1
$end
$timescale
  1ps
$end
$scope module tb_mux4to1 $end
$var reg 1 ! clk $end
$var wire 1 " out $end
$var reg 1 # a $end
$var reg 1 $ b $end
$var reg 1 % c $end
$var reg 1 & d $end
$var reg 1 ' s0 $end
$var reg 1 ( s1 $end
$var integer 32 ) i [31:0] $end
$var integer 32 * total_point [31:0] $end
$scope module uut $end
$var wire 1 + a $end
$var wire 1 , b $end
$var wire 1 - c $end
$var wire 1 . d $end
$var wire 1 / s0 $end
$var wire 1 0 s1 $end
$var wire 1 " out $end
$var wire 1 1 e $end
$var wire 1 2 f $end
$var wire 1 3 w1 $end
$var wire 1 4 w2 $end
$var wire 1 5 w3 $end
$var wire 1 6 w4 $end
$var wire 1 7 w5 $end
$var wire 1 8 w6 $end
$var wire 1 9 w7 $end
$var wire 1 : w8 $end
$var wire 1 ; w9 $end
$var wire 1 < w10 $end
$upscope $end
$upscope $end
$enddefinitions $end
#0
$dumpvars
0!
x"
x#
x$
x%
x&
x'
x(
bx )
b0 *
x+
x,
x-
x.
x/
x0
x1
x2
x3
x4
x5
x6
x7
x8
x9
x:
x;
x<
$end
#10000
0"
0#
0$
0%
0&
0'
0(
b0 )
0+
0,
0-
0.
0/
00
11
12
03
04
05
06
07
08
09
0:
0;
0<
#20000
1"
1#
b1 )
b1 *
1+
13
17
1;
#30000
0"
0#
1$
b10 )
b10 *
0+
1,
03
14
07
08
0;
#40000
1"
1#
b11 )
b11 *
1+
13
17
1;
#50000
0"
0#
0$
1%
b100 )
b100 *
0+
0,
1-
03
04
05
07
08
0;
#60000
1"
1#
b101 )
b101 *
1+
13
17
1;
#70000
0"
0#
1$
b110 )
b110 *
0+
1,
03
14
07
08
0;
#80000
1"
1#
b111 )
b111 *
1+
13
17
1;
#90000
0"
0#
0$
0%
1&
b1000 )
b1000 *
0+
0,
0-
1.
03
04
05
06
07
08
0;
#100000
1"
1#
b1001 )
b1001 *
1+
13
17
1;
#110000
0"
0#
1$
b1010 )
b1010 *
0+
1,
03
14
07
08
0;
#120000
1"
1#
b1011 )
b1011 *
1+
13
17
1;
#130000
0"
0#
0$
1%
b1100 )
b1100 *
0+
0,
1-
03
04
05
07
08
0;
#140000
1"
1#
b1101 )
b1101 *
1+
13
17
1;
#150000
0"
0#
1$
b1110 )
b1110 *
0+
1,
03
14
07
08
0;
#160000
1"
1#
b1111 )
b1111 *
1+
13
17
1;
#170000
0"
0#
0$
0%
0&
1'
b10000 )
b10000 *
0+
0,
0-
0.
1/
02
03
04
05
06
07
08
09
0:
0;
#180000
1#
b10001 )
b10001 *
1+
13
07
#190000
1"
0#
1$
b10010 )
b10010 *
0+
1,
03
14
07
18
1;
#200000
1#
b10011 )
b10011 *
1+
13
07
#210000
0"
0#
0$
1%
b10100 )
b10100 *
0+
0,
1-
03
04
05
07
08
0;
#220000
1#
b10101 )
b10101 *
1+
13
07
#230000
1"
0#
1$
b10110 )
b10110 *
0+
1,
03
14
07
18
1;
#240000
1#
b10111 )
b10111 *
1+
13
07
#250000
0"
0#
0$
0%
1&
b11000 )
b11000 *
0+
0,
0-
1.
03
04
05
06
07
08
0;
#260000
1#
b11001 )
b11001 *
1+
13
07
#270000
1"
0#
1$
b11010 )
b11010 *
0+
1,
03
14
07
18
1;
#280000
1#
b11011 )
b11011 *
1+
13
07
#290000
0"
0#
0$
1%
b11100 )
b11100 *
0+
0,
1-
03
04
05
07
08
0;
#300000
1#
b11101 )
b11101 *
1+
13
07
#310000
1"
0#
1$
b11110 )
b11110 *
0+
1,
03
14
07
18
1;
#320000
1#
b11111 )
b11111 *
1+
13
07
#330000
0"
0#
0$
0%
0&
0'
1(
b100000 )
b100000 *
0+
0,
0-
0.
0/
10
01
12
03
04
05
06
07
08
09
0:
0;
#340000
1#
b100001 )
b100001 *
1+
03
#350000
0#
1$
b100010 )
b100010 *
0+
1,
03
04
#360000
1#
b100011 )
b100011 *
1+
03
#370000
1"
0#
0$
1%
b100100 )
b100100 *
0+
0,
1-
03
04
15
19
1<
#380000
1#
b100101 )
b100101 *
1+
03
#390000
0#
1$
b100110 )
b100110 *
0+
1,
03
04
#400000
1#
b100111 )
b100111 *
1+
03
#410000
0"
0#
0$
0%
1&
b101000 )
b101000 *
0+
0,
0-
1.
03
04
05
16
09
0:
0<
#420000
1#
b101001 )
b101001 *
1+
03
#430000
0#
1$
b101010 )
b101010 *
0+
1,
03
04
#440000
1#
b101011 )
b101011 *
1+
03
#450000
1"
0#
0$
1%
b101100 )
b101100 *
0+
0,
1-
03
04
15
19
1<
#460000
1#
b101101 )
b101101 *
1+
03
#470000
0#
1$
b101110 )
b101110 *
0+
1,
03
04
#480000
1#
b101111 )
b101111 *
1+
03
#490000
0"
0#
0$
0%
0&
1'
b110000 )
b110000 *
0+
0,
0-
0.
1/
02
03
04
05
06
07
08
09
0:
0<
#500000
1#
b110001 )
b110001 *
1+
03
#510000
0#
1$
b110010 )
b110010 *
0+
1,
03
04
#520000
1#
b110011 )
b110011 *
1+
03
#530000
0#
0$
1%
b110100 )
b110100 *
0+
0,
1-
03
04
15
09
#540000
1#
b110101 )
b110101 *
1+
03
#550000
0#
1$
b110110 )
b110110 *
0+
1,
03
04
#560000
1#
b110111 )
b110111 *
1+
03
#570000
1"
0#
0$
0%
1&
b111000 )
b111000 *
0+
0,
0-
1.
03
04
05
16
09
1:
1<
#580000
1#
b111001 )
b111001 *
1+
03
#590000
0#
1$
b111010 )
b111010 *
0+
1,
03
04
#600000
1#
b111011 )
b111011 *
1+
03
#610000
0#
0$
1%
b111100 )
b111100 *
0+
0,
1-
03
04
15
09
#620000
1#
b111101 )
b111101 *
1+
03
#630000
0#
1$
b111110 )
b111110 *
0+
1,
03
04
#640000
1#
b111111 )
b111111 *
1+
03
#650000
b1000000 )
b1000000 *
