EE4363/belmo057_EE4363_lab1/belmo057_EE4363_lab1.srcs/sources_1/imports/EE4363/mux_4to1.v
`timescale 1ns / 1ps


module mux4to1(out, a, b, c, d, s0, s1);
    input a, b, c, d, s0, s1;
    output out;
    wire e,f,w1,w2,w3,w4,w5,w6,w7,w8,w9,w10;
    not (e,s1);
    not (f,s0);
    
    and (w1,a,e);
    and (w2,b,e);
    and (w3,c,s1);
    and (w4,d,s1);
    
    and (w5,w1,f);
    and (w6,w2,s0);
    and (w7,w3,f);
    and (w8,w4,s0);
    
    or (w9,w5,w6);
    or (w10,w7,w8);
    or (out,w9,w10);
    
   
endmodule

EE4363/belmo057_EE4363_lab1/belmo057_EE4363_lab1.srcs/sources_1/imports/EE4363/comparator_4b.v
`timescale 1ns / 1ps


module comparator_4b(A, B, less_or_eq);
    input [3:0] A, B;
    output less_or_eq;
    wire w1, w2, w3;
    
    mux4to1 g1(w1, 1, 0, 1, 1, A[0], B[0]);
    mux4to1 g2(w2, w1, 0, 1, w1, A[1], B[1]);
    mux4to1 g3(w3, w2, 0, 1, w2, A[2], B[2]);
    mux4to1 g4(less_or_eq , w3, 0, 1, w3, A[3], B[3]);
    
endmodule

EE4363/tb_comparator_4b.v
module tb_comparator_4b;

wire less_or_eq;
reg [3:0] A, B;
integer i;

comparator_4b uut (
    .less_or_eq    (    less_or_eq    ),
    .A      (    A      ),
    .B (B)
);

parameter PERIOD = 4;
integer total_point = 0;

initial begin
    $dumpfile("db_tb_comparator_4b.vcd");
    $dumpvars(0, tb_comparator_4b);
    #(PERIOD/2);

    for (i=0; i<=2**8-1; i=i+1)begin
        A = i[3:0];
        B = i[7:4];
        #(PERIOD/2);
        
        if (A > B) begin
            if (less_or_eq == 0) total_point = total_point + 1;
        end
            
        else begin
            if (less_or_eq == 1) total_point = total_point + 1;
        end
        end
end

endmodule

EE4363/belmo057_EE4363_lab1/belmo057_EE4363_lab1.sim/sim_1/behav/xsim/db_tb_comparator_4b.vcd
$date
   Tue Oct 11 20:24:32 2022
$end
$version
  2022.1
$end
$timescale
  1ps
$end
$scope module tb_comparator_4b $end
$var wire 1 ! less_or_eq $end
$var reg 4 " A [3:0] $end
$var reg 4 # B [3:0] $end
$var integer 32 $ i [31:0] $end
$var integer 32 % total_point [31:0] $end
$scope module uut $end
$var wire 4 & A [3:0] $end
$var wire 4 ' B [3:0] $end
$var wire 1 ! less_or_eq $end
$var wire 1 ( w1 $end
$var wire 1 ) w2 $end
$var wire 1 * w3 $end
$scope module g1 $end
$var wire 1 + a $end
$var wire 1 , b $end
$var wire 1 - c $end
$var wire 1 . d $end
$var wire 1 / s0 $end
$var wire 1 0 s1 $end
$var wire 1 ( out $end
$var wire 1 1 e $end
$var wire 1 2 f $end
$var wire 1 3 w1 $end
$var wire 1 4 w2 $end
$var wire 1 5 w3 $end
$var wire 1 6 w4 $end
$var wire 1 7 w5 $end
$var wire 1 8 w6 $end
$var wire 1 9 w7 $end
$var wire 1 : w8 $end
$var wire 1 ; w9 $end
$var wire 1 < w10 $end
$upscope $end
$scope module g2 $end
$var wire 1 ( a $end
$var wire 1 = b $end
$var wire 1 > c $end
$var wire 1 ( d $end
$var wire 1 ? s0 $end
$var wire 1 @ s1 $end
$var wire 1 ) out $end
$var wire 1 A e $end
$var wire 1 B f $end
$var wire 1 C w1 $end
$var wire 1 D w2 $end
$var wire 1 E w3 $end
$var wire 1 F w4 $end
$var wire 1 G w5 $end
$var wire 1 H w6 $end
$var wire 1 I w7 $end
$var wire 1 J w8 $end
$var wire 1 K w9 $end
$var wire 1 L w10 $end
$upscope $end
$scope module g3 $end
$var wire 1 ) a $end
$var wire 1 M b $end
$var wire 1 N c $end
$var wire 1 ) d $end
$var wire 1 O s0 $end
$var wire 1 P s1 $end
$var wire 1 * out $end
$var wire 1 Q e $end
$var wire 1 R f $end
$var wire 1 S w1 $end
$var wire 1 T w2 $end
$var wire 1 U w3 $end
$var wire 1 V w4 $end
$var wire 1 W w5 $end
$var wire 1 X w6 $end
$var wire 1 Y w7 $end
$var wire 1 Z w8 $end
$var wire 1 [ w9 $end
$var wire 1 \ w10 $end
$upscope $end
$scope module g4 $end
$var wire 1 * a $end
$var wire 1 ] b $end
$var wire 1 ^ c $end
$var wire 1 * d $end
$var wire 1 _ s0 $end
$var wire 1 ` s1 $end
$var wire 1 ! out $end
$var wire 1 a e $end
$var wire 1 b f $end
$var wire 1 c w1 $end
$var wire 1 d w2 $end
$var wire 1 e w3 $end
$var wire 1 f w4 $end
$var wire 1 g w5 $end
$var wire 1 h w6 $end
$var wire 1 i w7 $end
$var wire 1 j w8 $end
$var wire 1 k w9 $end
$var wire 1 l w10 $end
$upscope $end
$upscope $end
$upscope $end
$enddefinitions $end
#0
$dumpvars
x!
bx "
bx #
bx $
b0 %
bx &
bx '
x(
x)
x*
1+
0,
1-
1.
x/
x0
x1
x2
x3
04
x5
x6
x7
08
x9
x:
x;
x<
0=
1>
x?
x@
xA
xB
xC
0D
xE
xF
xG
0H
xI
xJ
xK
xL
0M
1N
xO
xP
xQ
xR
xS
0T
xU
xV
xW
0X
xY
xZ
x[
x\
0]
1^
x_
x`
xa
xb
xc
0d
xe
xf
xg
0h
xi
xj
xk
xl
$end
#2000
1!
b0 "
b0 #
b0 $
b0 &
b0 '
1(
1)
1*
0/
00
11
12
13
04
05
06
17
08
09
0:
1;
0<
0?
0@
1A
1B
1C
0D
0E
0F
1G
0H
0I
0J
1K
0L
0O
0P
1Q
1R
1S
0T
0U
0V
1W
0X
0Y
0Z
1[
0\
0_
0`
1a
1b
1c
0d
0e
0f
1g
0h
0i
0j
1k
0l
#4000
0!
b1 "
b0 #
b1 $
b1 %
b1 &
0(
0)
0*
1/
02
07
08
09
0:
0;
0?
0C
0F
0G
0K
0O
0S
0V
0W
0[
0_
0c
0f
0g
0k
#6000
b10 "
b0 #
b10 $
b10 %
b10 &
1(
0/
12
17
08
09
0:
1;
1?
0B
1C
0F
0G
0H
0I
0J
0O
0_
#8000
b11 "
b0 #
b11 $
b11 %
b11 &
0(
1/
02
07
08
09
0:
0;
1?
0C
0F
0G
0O
0_
#10000
b100 "
b0 #
b100 $
b100 %
b100 &
1(
1)
0/
12
17
08
09
0:
1;
0?
1B
1C
0F
1G
0H
0I
0J
1K
1O
0R
1S
0V
0W
0X
0Y
0Z
0_
#12000
b101 "
b0 #
b101 $
b101 %
b101 &
0(
0)
1/
02
07
08
09
0:
0;
0?
0C
0F
0G
0K
1O
0S
0V
0W
0_
#14000
b110 "
b0 #
b110 $
b110 %
b110 &
1(
0/
12
17
08
09
0:
1;
1?
0B
1C
0F
0G
0H
0I
0J
1O
0_
#16000
b111 "
b0 #
b111 $
b111 %
b111 &
0(
1/
02
07
08
09
0:
0;
1?
0C
0F
0G
1O
0_
#18000
b1000 "
b0 #
b1000 $
b1000 %
b1000 &
1(
1)
1*
0/
12
17
08
09
0:
1;
0?
1B
1C
0F
1G
0H
0I
0J
1K
0O
1R
1S
0V
1W
0X
0Y
0Z
1[
1_
0b
1c
0f
0g
0h
0i
0j
#20000
b1001 "
b0 #
b1001 $
b1001 %
b1001 &
0(
0)
0*
1/
02
07
08
09
0:
0;
0?
0C
0F
0G
0K
0O
0S
0V
0W
0[
1_
0c
0f
0g
#22000
b1010 "
b0 #
b1010 $
b1010 %
b1010 &
1(
0/
12
17
08
09
0:
1;
1?
0B
1C
0F
0G
0H
0I
0J
0O
1_
#24000
b1011 "
b0 #
b1011 $
b1011 %
b1011 &
0(
1/
02
07
08
09
0:
0;
1?
0C
0F
0G
0O
1_
#26000
b1100 "
b0 #
b1100 $
b1100 %
b1100 &
1(
1)
0/
12
17
08
09
0:
1;
0?
1B
1C
0F
1G
0H
0I
0J
1K
1O
0R
1S
0V
0W
0X
0Y
0Z
1_
#28000
b1101 "
b0 #
b1101 $
b1101 %
b1101 &
0(
0)
1/
02
07
08
09
0:
0;
0?
0C
0F
0G
0K
1O
0S
0V
0W
1_
#30000
b1110 "
b0 #
b1110 $
b1110 %
b1110 &
1(
0/
12
17
08
09
0:
1;
1?
0B
1C
0F
0G
0H
0I
0J
1O
1_
#32000
b1111 "
b0 #
b1111 $
b1111 %
b1111 &
0(
1/
02
07
08
09
0:
0;
1?
0C
0F
0G
1O
1_
#34000
1!
b0 "
b1 #
b10000 $
b10000 %
b0 &
b1 '
1(
1)
1*
0/
10
01
12
03
04
15
16
07
08
19
0:
1<
0?
0@
1B
1C
0F
1G
0H
0I
0J
1K
0O
0P
1R
1S
0V
1W
0X
0Y
0Z
1[
0_
0`
1b
1c
0f
1g
0h
0i
0j
1k
#36000
b1 "
b1 #
b10001 $
b10001 %
b1 &
1/
02
07
08
09
1:
1<
0?
0O
0_
#38000
0!
b10 "
b1 #
b10010 $
b10010 %
b10 &
0)
0*
0/
12
07
08
19
0:
1<
1?
0B
0G
0H
0I
0J
0K
0O
0S
0V
0W
0[
0_
0c
0f
0g
0k
#40000
b11 "
b1 #
b10011 $
b10011 %
b11 &
1/
02
07
08
09
1:
1<
1?
0O
0_
#42000
b100 "
b1 #
b10100 $
b10100 %
b100 &
1)
0/
12
07
08
19
0:
1<
0?
1B
1G
0H
0I
0J
1K
1O
0R
1S
0V
0W
0X
0Y
0Z
0_
#44000
b101 "
b1 #
b10101 $
b10101 %
b101 &
1/
02
07
08
09
1:
1<
0?
1O
0_
#46000
b110 "
b1 #
b10110 $
b10110 %
b110 &
0)
0/
12
07
08
19
0:
1<
1?
0B
0G
0H
0I
0J
0K
1O
0S
0V
0W
0_
#48000
b111 "
b1 #
b10111 $
b10111 %
b111 &
1/
02
07
08
09
1:
1<
1?
1O
0_
#50000
b1000 "
b1 #
b11000 $
b11000 %
b1000 &
1)
1*
0/
12
07
08
19
0:
1<
0?
1B
1G
0H
0I
0J
1K
0O
1R
1S
0V
1W
0X
0Y
0Z
1[
1_
0b
1c
0f
0g
0h
0i
0j
#52000
b1001 "
b1 #
b11001 $
b11001 %
b1001 &
1/
02
07
08
09
1:
1<
0?
0O
1_
#54000
b1010 "
b1 #
b11010 $
b11010 %
b1010 &
0)
0*
0/
12
07
08
19
0:
1<
1?
0B
0G
0H
0I
0J
0K
0O
0S
0V
0W
0[
1_
0c
0f
0g
#56000
b1011 "
b1 #
b11011 $
b11011 %
b1011 &
1/
02
07
08
09
1:
1<
1?
0O
1_
#58000
b1100 "
b1 #
b11100 $
b11100 %
b1100 &
1)
0/
12
07
08
19
0:
1<
0?
1B
1G
0H
0I
0J
1K
1O
0R
1S
0V
0W
0X
0Y
0Z
1_
#60000
b1101 "
b1 #
b11101 $
b11101 %
b1101 &
1/
02
07
08
09
1:
1<
0?
1O
1_
#62000
b1110 "
b1 #
b11110 $
b11110 %
b1110 &
0)
0/
12
07
08
19
0:
1<
1?
0B
0G
0H
0I
0J
0K
1O
0S
0V
0W
1_
#64000
b1111 "
b1 #
b11111 $
b11111 %
b1111 &
1/
02
07
08
09
1:
1<
1?
1O
1_
#66000
1!
b0 "
b10 #
b100000 $
b100000 %
b0 &
b10 '
1(
1)
1*
0/
00
11
12
13
04
05
06
17
08
09
0:
1;
0<
0?
1@
0A
1B
0C
0D
1E
1F
0G
0H
1I
0J
1L
0O
0P
1R
1S
0V
1W
0X
0Y
0Z
1[
0_
0`
1b
1c
0f
1g
0h
0i
0j
1k
#68000
b1 "
b10 #
b100001 $
b100001 %
b1 &
0(
1/
02
07
08
09
0:
0;
0?
0C
0F
0J
0O
0_
#70000
1!
b10 "
b10 #
b100010 $
b100010 %
b10 &
1(
1)
1*
0/
12
17
08
09
0:
1;
1?
0B
0C
1F
0G
0H
0I
1J
1L
0O
1S
0V
1W
1[
0_
1c
0f
1g
1k
#72000
0!
b11 "
b10 #
b100011 $
b100011 %
b11 &
0(
0)
0*
1/
02
07
08
09
0:
0;
1?
0C
0F
0J
0L
0O
0S
0V
0W
0[
0_
0c
0f
0g
0k
#74000
b100 "
b10 #
b100100 $
b100100 %
b100 &
1(
1)
0/
12
17
08
09
0:
1;
0?
1B
0C
1F
0G
0H
1I
0J
1L
1O
0R
1S
0V
0W
0X
0Y
0Z
0_
#76000
b101 "
b10 #
b100101 $
b100101 %
b101 &
0(
1/
02
07
08
09
0:
0;
0?
0C
0F
0J
1O
0_
#78000
b110 "
b10 #
b100110 $
b100110 %
b110 &
1(
1)
0/
12
17
08
09
0:
1;
1?
0B
0C
1F
0G
0H
0I
1J
1L
1O
1S
0V
0W
0_
#80000
b111 "
b10 #
b100111 $
b100111 %
b111 &
0(
0)
1/
02
07
08
09
0:
0;
1?
0C
0F
0J
0L
1O
0S
0V
0W
0_
#82000
b1000 "
b10 #
b101000 $
b101000 %
b1000 &
1(
1)
1*
0/
12
17
08
09
0:
1;
0?
1B
0C
1F
0G
0H
1I
0J
1L
0O
1R
1S
0V
1W
0X
0Y
0Z
1[
1_
0b
1c
0f
0g
0h
0i
0j
#84000
b1001 "
b10 #
b101001 $
b101001 %
b1001 &
0(
1/
02
07
08
09
0:
0;
0?
0C
0F
0J
0O
1_
#86000
b1010 "
b10 #
b101010 $
b101010 %
b1010 &
1(
1)
1*
0/
12
17
08
09
0:
1;
1?
0B
0C
1F
0G
0H
0I
1J
1L
0O
1S
0V
1W
1[
1_
1c
0f
0g
#88000
b1011 "
b10 #
b101011 $
b101011 %
b1011 &
0(
0)
0*
1/
02
07
08
09
0:
0;
1?
0C
0F
0J
0L
0O
0S
0V
0W
0[
1_
0c
0f
0g
#90000
b1100 "
b10 #
b101100 $
b101100 %
b1100 &
1(
1)
0/
12
17
08
09
0:
1;
0?
1B
0C
1F
0G
0H
1I
0J
1L
1O
0R
1S
0V
0W
0X
0Y
0Z
1_
#92000
b1101 "
b10 #
b101101 $
b101101 %
b1101 &
0(
1/
02
07
08
09
0:
0;
0?
0C
0F
0J
1O
1_
#94000
b1110 "
b10 #
b101110 $
b101110 %
b1110 &
1(
1)
0/
12
17
08
09
0:
1;
1?
0B
0C
1F
0G
0H
0I
1J
1L
1O
1S
0V
0W
1_
#96000
b1111 "
b10 #
b101111 $
b101111 %
b1111 &
0(
0)
1/
02
07
08
09
0:
0;
1?
0C
0F
0J
0L
1O
0S
0V
0W
1_
#98000
1!
b0 "
b11 #
b110000 $
b110000 %
b0 &
b11 '
1(
1)
1*
0/
10
01
12
03
04
15
16
07
08
19
0:
1<
0?
1@
1B
0C
1F
0G
0H
1I
0J
1L
0O
0P
1R
1S
0V
1W
0X
0Y
0Z
1[
0_
0`
1b
1c
0f
1g
0h
0i
0j
1k
#100000
b1 "
b11 #
b110001 $
b110001 %
b1 &
1/
02
07
08
09
1:
1<
0?
0O
0_
#102000
b10 "
b11 #
b110010 $
b110010 %
b10 &
0/
12
07
08
19
0:
1<
1?
0B
0G
0H
0I
1J
1L
0O
0_
#104000
b11 "
b11 #
b110011 $
b110011 %
b11 &
1/
02
07
08
09
1:
1<
1?
0O
0_
#106000
0!
b100 "
b11 #
b110100 $
b110100 %
b100 &
0*
0/
12
07
08
19
0:
1<
0?
1B
0G
0H
1I
0J
1L
1O
0R
0W
0X
0Y
0Z
0[
0_
0c
0f
0g
0k
#108000
b101 "
b11 #
b110101 $
b110101 %
b101 &
1/
02
07
08
09
1:
1<
0?
1O
0_
#110000
b110 "
b11 #
b110110 $
b110110 %
b110 &
0/
12
07
08
19
0:
1<
1?
0B
0G
0H
0I
1J
1L
1O
0_
#112000
b111 "
b11 #
b110111 $
b110111 %
b111 &
1/
02
07
08
09
1:
1<
1?
1O
0_
#114000
b1000 "
b11 #
b111000 $
b111000 %
b1000 &
1*
0/
12
07
08
19
0:
1<
0?
1B
0G
0H
1I
0J
1L
0O
1R
1W
0X
0Y
0Z
1[
1_
0b
1c
0f
0g
0h
0i
0j
#116000
b1001 "
b11 #
b111001 $
b111001 %
b1001 &
1/
02
07
08
09
1:
1<
0?
0O
1_
#118000
b1010 "
b11 #
b111010 $
b111010 %
b1010 &
0/
12
07
08
19
0:
1<
1?
0B
0G
0H
0I
1J
1L
0O
1_
#120000
b1011 "
b11 #
b111011 $
b111011 %
b1011 &
1/
02
07
08
09
1:
1<
1?
0O
1_
#122000
b1100 "
b11 #
b111100 $
b111100 %
b1100 &
0*
0/
12
07
08
19
0:
1<
0?
1B
0G
0H
1I
0J
1L
1O
0R
0W
0X
0Y
0Z
0[
1_
0c
0f
0g
#124000
b1101 "
b11 #
b111101 $
b111101 %
b1101 &
1/
02
07
08
09
1:
1<
0?
1O
1_
#126000
b1110 "
b11 #
b111110 $
b111110 %
b1110 &
0/
12
07
08
19
0:
1<
1?
0B
0G
0H
0I
1J
1L
1O
1_
#128000
b1111 "
b11 #
b111111 $
b111111 %
b1111 &
1/
02
07
08
09
1:
1<
1?
1O
1_
#130000
1!
b0 "
b100 #
b1000000 $
b1000000 %
b0 &
b100 '
1(
1)
1*
0/
00
11
12
13
04
05
06
17
08
09
0:
1;
0<
0?
0@
1A
1B
1C
0D
0E
0F
1G
0H
0I
0J
1K
0L
0O
1P
0Q
1R
0S
0T
1U
1V
0W
0X
1Y
0Z
1\
0_
0`
1b
1c
0f
1g
0h
0i
0j
1k
#132000
b1 "
b100 #
b1000001 $
b1000001 %
b1 &
0(
0)
1/
02
07
08
09
0:
0;
0?
0C
0F
0G
0K
0O
0S
0V
0Z
0_
#134000
b10 "
b100 #
b1000010 $
b1000010 %
b10 &
1(
0/
12
17
08
09
0:
1;
1?
0B
1C
0F
0G
0H
0I
0J
0O
0_
#136000
b11 "
b100 #
b1000011 $
b1000011 %
b11 &
0(
1/
02
07
08
09
0:
0;
1?
0C
0F
0G
0O
0_
#138000
1!
b100 "
b100 #
b1000100 $
b1000100 %
b100 &
1(
1)
1*
0/
12
17
08
09
0:
1;
0?
1B
1C
0F
1G
0H
0I
0J
1K
1O
0R
0S
1V
0W
0X
0Y
1Z
1\
0_
1c
0f
1g
1k
#140000
0!
b101 "
b100 #
b1000101 $
b1000101 %
b101 &
0(
0)
0*
1/
02
07
08
09
0:
0;
0?
0C
0F
0G
0K
1O
0S
0V
0Z
0\
0_
0c
0f
0g
0k
#142000
b110 "
b100 #
b1000110 $
b1000110 %
b110 &
1(
0/
12
17
08
09
0:
1;
1?
0B
1C
0F
0G
0H
0I
0J
1O
0_
#144000
b111 "
b100 #
b1000111 $
b1000111 %
b111 &
0(
1/
02
07
08
09
0:
0;
1?
0C
0F
0G
1O
0_
#146000
b1000 "
b100 #
b1001000 $
b1001000 %
b1000 &
1(
1)
1*
0/
12
17
08
09
0:
1;
0?
1B
1C
0F
1G
0H
0I
0J
1K
0O
1R
0S
1V
0W
0X
1Y
0Z
1\
1_
0b
1c
0f
0g
0h
0i
0j
#148000
b1001 "
b100 #
b1001001 $
b1001001 %
b1001 &
0(
0)
1/
02
07
08
09
0:
0;
0?
0C
0F
0G
0K
0O
0S
0V
0Z
1_
#150000
b1010 "
b100 #
b1001010 $
b1001010 %
b1010 &
1(
0/
12
17
08
09
0:
1;
1?
0B
1C
0F
0G
0H
0I
0J
0O
1_
#152000
b1011 "
b100 #
b1001011 $
b1001011 %
b1011 &
0(
1/
02
07
08
09
0:
0;
1?
0C
0F
0G
0O
1_
#154000
b1100 "
b100 #
b1001100 $
b1001100 %
b1100 &
1(
1)
1*
0/
12
17
08
09
0:
1;
0?
1B
1C
0F
1G
0H
0I
0J
1K
1O
0R
0S
1V
0W
0X
0Y
1Z
1\
1_
1c
0f
0g
#156000
b1101 "
b100 #
b1001101 $
b1001101 %
b1101 &
0(
0)
0*
1/
02
07
08
09
0:
0;
0?
0C
0F
0G
0K
1O
0S
0V
0Z
0\
1_
0c
0f
0g
#158000
b1110 "
b100 #
b1001110 $
b1001110 %
b1110 &
1(
0/
12
17
08
09
0:
1;
1?
0B
1C
0F
0G
0H
0I
0J
1O
1_
#160000
b1111 "
b100 #
b1001111 $
b1001111 %
b1111 &
0(
1/
02
07
08
09
0:
0;
1?
0C
0F
0G
1O
1_
#162000
1!
b0 "
b101 #
b1010000 $
b1010000 %
b0 &
b101 '
1(
1)
1*
0/
10
01
12
03
04
15
16
07
08
19
0:
1<
0?
0@
1B
1C
0F
1G
0H
0I
0J
1K
0O
1P
1R
0S
1V
0W
0X
1Y
0Z
1\
0_
0`
1b
1c
0f
1g
0h
0i
0j
1k
#164000
b1 "
b101 #
b1010001 $
b1010001 %
b1 &
1/
02
07
08
09
1:
1<
0?
0O
0_
#166000
b10 "
b101 #
b1010010 $
b1010010 %
b10 &
0)
0/
12
07
08
19
0:
1<
1?
0B
0G
0H
0I
0J
0K
0O
0S
0V
0Z
0_
#168000
b11 "
b101 #
b1010011 $
b1010011 %
b11 &
1/
02
07
08
09
1:
1<
1?
0O
0_
#170000
1!
b100 "
b101 #
b1010100 $
b1010100 %
b100 &
1)
1*
0/
12
07
08
19
0:
1<
0?
1B
1G
0H
0I
0J
1K
1O
0R
0S
1V
0W
0X
0Y
1Z
1\
0_
1c
0f
1g
1k
#172000
b101 "
b101 #
b1010101 $
b1010101 %
b101 &
1/
02
07
08
09
1:
1<
0?
1O
0_
#174000
0!
b110 "
b101 #
b1010110 $
b1010110 %
b110 &
0)
0*
0/
12
07
08
19
0:
1<
1?
0B
0G
0H
0I
0J
0K
1O
0S
0V
0Z
0\
0_
0c
0f
0g
0k
#176000
b111 "
b101 #
b1010111 $
b1010111 %
b111 &
1/
02
07
08
09
1:
1<
1?
1O
0_
#178000
b1000 "
b101 #
b1011000 $
b1011000 %
b1000 &
1)
1*
0/
12
07
08
19
0:
1<
0?
1B
1G
0H
0I
0J
1K
0O
1R
0S
1V
0W
0X
1Y
0Z
1\
1_
0b
1c
0f
0g
0h
0i
0j
#180000
b1001 "
b101 #
b1011001 $
b1011001 %
b1001 &
1/
02
07
08
09
1:
1<
0?
0O
1_
#182000
b1010 "
b101 #
b1011010 $
b1011010 %
b1010 &
0)
0/
12
07
08
19
0:
1<
1?
0B
0G
0H
0I
0J
0K
0O
0S
0V
0Z
1_
#184000
b1011 "
b101 #
b1011011 $
b1011011 %
b1011 &
1/
02
07
08
09
1:
1<
1?
0O
1_
#186000
b1100 "
b101 #
b1011100 $
b1011100 %
b1100 &
1)
1*
0/
12
07
08
19
0:
1<
0?
1B
1G
0H
0I
0J
1K
1O
0R
0S
1V
0W
0X
0Y
1Z
1\
1_
1c
0f
0g
#188000
b1101 "
b101 #
b1011101 $
b1011101 %
b1101 &
1/
02
07
08
09
1:
1<
0?
1O
1_
#190000
b1110 "
b101 #
b1011110 $
b1011110 %
b1110 &
0)
0*
0/
12
07
08
19
0:
1<
1?
0B
0G
0H
0I
0J
0K
1O
0S
0V
0Z
0\
1_
0c
0f
0g
#192000
b1111 "
b101 #
b1011111 $
b1011111 %
b1111 &
1/
02
07
08
09
1:
1<
1?
1O
1_
#194000
1!
b0 "
b110 #
b1100000 $
b1100000 %
b0 &
b110 '
1(
1)
1*
0/
00
11
12
13
04
05
06
17
08
09
0:
1;
0<
0?
1@
0A
1B
0C
0D
1E
1F
0G
0H
1I
0J
1L
0O
1P
1R
0S
1V
0W
0X
1Y
0Z
1\
0_
0`
1b
1c
0f
1g
0h
0i
0j
1k
#196000
b1 "
b110 #
b1100001 $
b1100001 %
b1 &
0(
1/
02
07
08
09
0:
0;
0?
0C
0F
0J
0O
0_
#198000
b10 "
b110 #
b1100010 $
b1100010 %
b10 &
1(
1)
0/
12
17
08
09
0:
1;
1?
0B
0C
1F
0G
0H
0I
1J
1L
0O
0S
1V
0Z
0_
#200000
b11 "
b110 #
b1100011 $
b1100011 %
b11 &
0(
0)
1/
02
07
08
09
0:
0;
1?
0C
0F
0J
0L
0O
0S
0V
0Z
0_
#202000
1!
b100 "
b110 #
b1100100 $
b1100100 %
b100 &
1(
1)
1*
0/
12
17
08
09
0:
1;
0?
1B
0C
1F
0G
0H
1I
0J
1L
1O
0R
0S
1V
0W
0X
0Y
1Z
1\
0_
1c
0f
1g
1k
#204000
b101 "
b110 #
b1100101 $
b1100101 %
b101 &
0(
1/
02
07
08
09
0:
0;
0?
0C
0F
0J
1O
0_
#206000
1!
b110 "
b110 #
b1100110 $
b1100110 %
b110 &
1(
1)
1*
0/
12
17
08
09
0:
1;
1?
0B
0C
1F
0G
0H
0I
1J
1L
1O
0S
1V
1Z
1\
0_
1c
0f
1g
1k
#208000
0!
b111 "
b110 #
b1100111 $
b1100111 %
b111 &
0(
0)
0*
1/
02
07
08
09
0:
0;
1?
0C
0F
0J
0L
1O
0S
0V
0Z
0\
0_
0c
0f
0g
0k
#210000
b1000 "
b110 #
b1101000 $
b1101000 %
b1000 &
1(
1)
1*
0/
12
17
08
09
0:
1;
0?
1B
0C
1F
0G
0H
1I
0J
1L
0O
1R
0S
1V
0W
0X
1Y
0Z
1\
1_
0b
1c
0f
0g
0h
0i
0j
#212000
b1001 "
b110 #
b1101001 $
b1101001 %
b1001 &
0(
1/
02
07
08
09
0:
0;
0?
0C
0F
0J
0O
1_
#214000
b1010 "
b110 #
b1101010 $
b1101010 %
b1010 &
1(
1)
0/
12
17
08
09
0:
1;
1?
0B
0C
1F
0G
0H
0I
1J
1L
0O
0S
1V
0Z
1_
#216000
b1011 "
b110 #
b1101011 $
b1101011 %
b1011 &
0(
0)
1/
02
07
08
09
0:
0;
1?
0C
0F
0J
0L
0O
0S
0V
0Z
1_
#218000
b1100 "
b110 #
b1101100 $
b1101100 %
b1100 &
1(
1)
1*
0/
12
17
08
09
0:
1;
0?
1B
0C
1F
0G
0H
1I
0J
1L
1O
0R
0S
1V
0W
0X
0Y
1Z
1\
1_
1c
0f
0g
#220000
b1101 "
b110 #
b1101101 $
b1101101 %
b1101 &
0(
1/
02
07
08
09
0:
0;
0?
0C
0F
0J
1O
1_
#222000
b1110 "
b110 #
b1101110 $
b1101110 %
b1110 &
1(
1)
1*
0/
12
17
08
09
0:
1;
1?
0B
0C
1F
0G
0H
0I
1J
1L
1O
0S
1V
1Z
1\
1_
1c
0f
0g
#224000
b1111 "
b110 #
b1101111 $
b1101111 %
b1111 &
0(
0)
0*
1/
02
07
08
09
0:
0;
1?
0C
0F
0J
0L
1O
0S
0V
0Z
0\
1_
0c
0f
0g
#226000
1!
b0 "
b111 #
b1110000 $
b1110000 %
b0 &
b111 '
1(
1)
1*
0/
10
01
12
03
04
15
16
07
08
19
0:
1<
0?
1@
1B
0C
1F
0G
0H
1I
0J
1L
0O
1P
1R
0S
1V
0W
0X
1Y
0Z
1\
0_
0`
1b
1c
0f
1g
0h
0i
0j
1k
#228000
b1 "
b111 #
b1110001 $
b1110001 %
b1 &
1/
02
07
08
09
1:
1<
0?
0O
0_
#230000
b10 "
b111 #
b1110010 $
b1110010 %
b10 &
0/
12
07
08
19
0:
1<
1?
0B
0G
0H
0I
1J
1L
0O
0_
#232000
b11 "
b111 #
b1110011 $
b1110011 %
b11 &
1/
02
07
08
09
1:
1<
1?
0O
0_
#234000
b100 "
b111 #
b1110100 $
b1110100 %
b100 &
0/
12
07
08
19
0:
1<
0?
1B
0G
0H
1I
0J
1L
1O
0R
0W
0X
0Y
1Z
1\
0_
#236000
b101 "
b111 #
b1110101 $
b1110101 %
b101 &
1/
02
07
08
09
1:
1<
0?
1O
0_
#238000
b110 "
b111 #
b1110110 $
b1110110 %
b110 &
0/
12
07
08
19
0:
1<
1?
0B
0G
0H
0I
1J
1L
1O
0_
#240000
b111 "
b111 #
b1110111 $
b1110111 %
b111 &
1/
02
07
08
09
1:
1<
1?
1O
0_
#242000
0!
b1000 "
b111 #
b1111000 $
b1111000 %
b1000 &
0/
12
07
08
19
0:
1<
0?
1B
0G
0H
1I
0J
1L
0O
1R
0W
0X
1Y
0Z
1\
1_
0b
0g
0h
0i
0j
0k
#244000
b1001 "
b111 #
b1111001 $
b1111001 %
b1001 &
1/
02
07
08
09
1:
1<
0?
0O
1_
#246000
b1010 "
b111 #
b1111010 $
b1111010 %
b1010 &
0/
12
07
08
19
0:
1<
1?
0B
0G
0H
0I
1J
1L
0O
1_
#248000
b1011 "
b111 #
b1111011 $
b1111011 %
b1011 &
1/
02
07
08
09
1:
1<
1?
0O
1_
#250000
b1100 "
b111 #
b1111100 $
b1111100 %
b1100 &
0/
12
07
08
19
0:
1<
0?
1B
0G
0H
1I
0J
1L
1O
0R
0W
0X
0Y
1Z
1\
1_
#252000
b1101 "
b111 #
b1111101 $
b1111101 %
b1101 &
1/
02
07
08
09
1:
1<
0?
1O
1_
#254000
b1110 "
b111 #
b1111110 $
b1111110 %
b1110 &
0/
12
07
08
19
0:
1<
1?
0B
0G
0H
0I
1J
1L
1O
1_
#256000
b1111 "
b111 #
b1111111 $
b1111111 %
b1111 &
1/
02
07
08
09
1:
1<
1?
1O
1_
#258000
1!
b0 "
b1000 #
b10000000 $
b10000000 %
b0 &
b1000 '
1(
1)
1*
0/
00
11
12
13
04
05
06
17
08
09
0:
1;
0<
0?
0@
1A
1B
1C
0D
0E
0F
1G
0H
0I
0J
1K
0L
0O
0P
1Q
1R
1S
0T
0U
0V
1W
0X
0Y
0Z
1[
0\
0_
1`
0a
1b
0c
0d
1e
1f
0g
0h
1i
0j
1l
#260000
b1 "
b1000 #
b10000001 $
b10000001 %
b1 &
0(
0)
0*
1/
02
07
08
09
0:
0;
0?
0C
0F
0G
0K
0O
0S
0V
0W
0[
0_
0c
0f
0j
#262000
b10 "
b1000 #
b10000010 $
b10000010 %
b10 &
1(
0/
12
17
08
09
0:
1;
1?
0B
1C
0F
0G
0H
0I
0J
0O
0_
#264000
b11 "
b1000 #
b10000011 $
b10000011 %
b11 &
0(
1/
02
07
08
09
0:
0;
1?
0C
0F
0G
0O
0_
